README.md
setup.py
dtn_tvg_util.egg-info/PKG-INFO
dtn_tvg_util.egg-info/SOURCES.txt
dtn_tvg_util.egg-info/dependency_links.txt
dtn_tvg_util.egg-info/requires.txt
dtn_tvg_util.egg-info/top_level.txt
test/__init__.py
test/test_contact_plan_extended.py
test/test_contact_plan_simple.py
test/test_transmission_plan.py
test/test_tvg.py
test/test_util.py
test/ring_road/__init__.py
test/ring_road/test_contact_plan.py
test/ring_road/test_scenario.py
tvgutil/__init__.py
tvgutil/contact_plan.py
tvgutil/transmission_plan.py
tvgutil/tvg.py
tvgutil/util.py
tvgutil/ring_road/__init__.py
tvgutil/ring_road/contact_plan.py
tvgutil/ring_road/gslist.py
tvgutil/ring_road/scenario.py
tvgutil/tools/__init__.py
tvgutil/tools/convert_ftvg_to_ptvg.py
tvgutil/tools/convert_legacy_contact_plan_to_tvg.py
tvgutil/tools/convert_legacy_tvg_to_tvg.py
tvgutil/tools/convert_ptvg_to_ftvg.py
tvgutil/tools/create_gs_list.py
tvgutil/tools/create_rr_scenario.py
tvgutil/tools/create_rr_tvg.py
tvgutil/tools/create_transmission_plan.py
tvgutil/tools/fix_rr_scenario_tle_checksums.py