Metadata-Version: 2.1
Name: dtn-tvg-util
Version: 0.1.5
Summary: A Python module providing functions for the representation of DTNs based on time-varying network graphs. Supports Python 2.7 and Python 3.4+.
Home-page: https://gitlab.com/d3tn/dtn-tvg-util
Author: Felix Walter
Author-email: code@felix-walter.eu
License: UNKNOWN
Platform: UNKNOWN
Classifier: Programming Language :: Python :: 2
Classifier: Programming Language :: Python :: 3
Classifier: License :: OSI Approved :: MIT License
Classifier: Operating System :: OS Independent
Provides-Extra: ring_road
Provides-Extra: gs_placement
